AUTHORS.txt
CHANGES.rst
LICENSE.txt
MANIFEST.in
README.rst
setup.py
django_mobile/__init__.py
django_mobile/conf.py
django_mobile/session.py
django_mobile/session_settings.py
django_mobile/cache/__init__.py
django_mobile/cache/middleware.py
django_mobile_threadsafe.egg-info/PKG-INFO
django_mobile_threadsafe.egg-info/SOURCES.txt
django_mobile_threadsafe.egg-info/dependency_links.txt
django_mobile_threadsafe.egg-info/requires.txt
django_mobile_threadsafe.egg-info/top_level.txt