Metadata-Version: 1.0
Name: django-mobile-threadsafe
Version: 0.3
Summary: Detect mobile browsers and serve different template flavours to them.
Home-page: https://github.com/demidov91/django-mobile
Author: Gregor Müllegger, Demodov Dmitry
Author-email: demidov91@mail.ru
License: BSD
Platform: UNKNOWN
Classifier: Environment :: Web Environment
Classifier: Framework :: Django
Classifier: Intended Audience :: Developers
Classifier: License :: OSI Approved :: BSD License
Classifier: Natural Language :: English
Classifier: Operating System :: OS Independent
Classifier: Programming Language :: Python
